biquad_filters-0.1.3.dist-info/licenses/LICENSE
biquads/__init__.py
biquads/filters/__init__.py
biquads/filters/all_pass.py
biquads/filters/band_pass.py
biquads/filters/biquad.py
biquads/filters/filter.py
biquads/filters/high_pass.py
biquads/filters/high_shelf.py
biquads/filters/low_pass.py
biquads/filters/low_shelf.py
biquads/filters/notch.py
biquads/filters/peaking_eq.py
biquad_filters-0.1.3.dist-info/METADATA
biquad_filters-0.1.3.dist-info/WHEEL
biquad_filters-0.1.3.dist-info/top_level.txt
biquad_filters-0.1.3.dist-info/RECORD
