Metadata-Version: 2.4
Name: biquad-filters
Version: 0.1.3
Summary: A simple package for creating biquad filters
Author-email: Alex Parisi <alex@atparisi.com>
Project-URL: Homepage, https://github.com/alex-parisi/biquad-filters
Project-URL: Issues, https://github.com/alex-parisi/biquad-filters/issues
Classifier: Programming Language :: Python :: 3
Classifier: Operating System :: OS Independent
Classifier: License :: OSI Approved :: MIT License
Requires-Python: >=3.10
License-File: LICENSE
Dynamic: license-file
